conf/.template
help.txt
main.py
signup/__init__.py
signup/__main__.py
signup/_config.py
signup/info.py
signup/login.py
signup/temperature.py
signup/utils.py
ahstu_sign_up-1.1.1a1.dist-info/entry_points.txt
ahstu_sign_up-1.1.1a1.dist-info/LICENSE
ahstu_sign_up-1.1.1a1.dist-info/WHEEL
ahstu_sign_up-1.1.1a1.dist-info/METADATA
ahstu_sign_up-1.1.1a1.dist-info/RECORD
