Metadata-Version: 2.1
Name: ahstu-sign-up
Version: 1.1.1a1
Summary: a simple script to deal with daily sign-up in AHSTU
Home-page: https://github.com/NoSimpleApple/ahstu_sign_up
License: MIT
Keywords: ahstu,automatic
Author: uncle_hoshino
Author-email: hgenaaaa@gmail.com
Requires-Python: >=3.10.0,<3.11.0
Classifier: License :: OSI Approved :: MIT License
Classifier: Programming Language :: Python :: 3
Classifier: Programming Language :: Python :: 3.10
Requires-Dist: lxml (>=4.8)
Requires-Dist: requests (>=2.28.1)
Project-URL: Repository, https://github.com/NoSimpleApple/ahstu_sign_up
